flake8_unused_fstrings/__init__.py
flake8_unused_fstrings/py.typed
flake8_unused_fstrings-2.0.0.dist-info/LICENSE
flake8_unused_fstrings-2.0.0.dist-info/METADATA
flake8_unused_fstrings-2.0.0.dist-info/WHEEL
flake8_unused_fstrings-2.0.0.dist-info/entry_points.txt
flake8_unused_fstrings-2.0.0.dist-info/RECORD
