Metadata-Version: 2.2
Name: flake8-unused-fstrings
Version: 2.0.0
Summary: Flake8 plugin to catch f-strings with no fields.
Author-email: adam hitchcock <adam+python@northisup.com>
License: ISCL
Home-page: https://github.com/python-formate/flake8-unused-fstrings
Project-URL: Issue Tracker, https://github.com/python-formate/flake8-unused-fstrings/issues
Project-URL: Source Code, https://github.com/python-formate/flake8-unused-fstrings
Platform: Windows
Platform: macOS
Platform: Linux
Classifier: Development Status :: 5 - Production/Stable
Classifier: Framework :: Flake8
Classifier: Intended Audience :: Developers
Classifier: License :: OSI Approved :: ISC License (ISCL)
Classifier: Natural Language :: English
Classifier: Operating System :: OS Independent
Classifier: Programming Language :: Python
Classifier: Programming Language :: Python :: 3 :: Only
Classifier: Programming Language :: Python :: 3.8
Classifier: Programming Language :: Python :: 3.9
Classifier: Programming Language :: Python :: 3.10
Classifier: Programming Language :: Python :: 3.11
Classifier: Programming Language :: Python :: 3.12
Classifier: Programming Language :: Python :: 3.13
Classifier: Programming Language :: Python :: Implementation :: CPython
Classifier: Typing :: Typed
Requires-Python: >=3.8
Requires-Dist: flake8-helper>=0.1.1
